lifecyclelogging/__init__.py
lifecyclelogging/const.py
lifecyclelogging/handlers.py
lifecyclelogging/log_types.py
lifecyclelogging/logging.py
lifecyclelogging/py.typed
lifecyclelogging/utils.py
lifecyclelogging-0.2.1.dist-info/METADATA
lifecyclelogging-0.2.1.dist-info/WHEEL
lifecyclelogging-0.2.1.dist-info/RECORD
