Metadata-Version: 2.4
Name: lifecyclelogging
Version: 0.2.1
Summary: A comprehensive logging utility for managing application lifecycle logs
Project-URL: Documentation, https://github.com/jbcom/lifecyclelogging#readme
Project-URL: Issues, https://github.com/jbcom/lifecyclelogging/issues
Project-URL: Source, https://github.com/jbcom/lifecyclelogging
Author-email: Jon Bogaty <jon@jonbogaty.com>
Maintainer-email: Jon Bogaty <jon@jonbogaty.com>
License: MIT
Keywords: debug,lifecycle,logging
Classifier: Development Status :: 5 - Production/Stable
Classifier: Intended Audience :: Developers
Classifier: License :: OSI Approved :: MIT License
Classifier: Programming Language :: Python :: 3
Classifier: Programming Language :: Python :: 3.9
Classifier: Programming Language :: Python :: 3.10
Classifier: Programming Language :: Python :: 3.11
Classifier: Programming Language :: Python :: 3.12
Classifier: Programming Language :: Python :: 3.13
Classifier: Typing :: Typed
Requires-Python: >=3.9
Requires-Dist: extended-data-types>=2025.11.164
Requires-Dist: rich>=13.0.0
Requires-Dist: typing-extensions>=4.0.0; python_version < '3.10'
Provides-Extra: docs
Requires-Dist: docutils>=0.17; extra == 'docs'
Requires-Dist: myst-parser>=3.0.1; extra == 'docs'
Requires-Dist: sphinx-autodoc2>=0.5.0; extra == 'docs'
Requires-Dist: sphinx>=7.0; extra == 'docs'
Requires-Dist: sphinxawesome-theme>=5.2.0; extra == 'docs'
Provides-Extra: tests
Requires-Dist: coverage[toml]>=7.6.0; extra == 'tests'
Requires-Dist: hypothesis>=6.0.0; extra == 'tests'
Requires-Dist: pytest-cov>=4.0; extra == 'tests'
Requires-Dist: pytest-xdist>=3.6.1; extra == 'tests'
Requires-Dist: pytest>=7.0; extra == 'tests'
Provides-Extra: typing
Requires-Dist: mypy>=1.0.0; extra == 'typing'
